mopidy_debugrel/__init__.py
mopidy_debugrel/ext.conf
mopidy_debugrel-1.0.1.dist-info/LICENSE
mopidy_debugrel-1.0.1.dist-info/METADATA
mopidy_debugrel-1.0.1.dist-info/WHEEL
mopidy_debugrel-1.0.1.dist-info/entry_points.txt
mopidy_debugrel-1.0.1.dist-info/top_level.txt
mopidy_debugrel-1.0.1.dist-info/RECORD
