Metadata-Version: 2.2
Name: mopidy-debugrel
Version: 1.0.1
Summary: Mopidy extension that provides a debugging Read-Eval loop over http
Author-email: Mathias Millet <mathias@mmill.eu>
License: Apache-2.0
Project-URL: Homepage, https://github.com/sapristi/mopidy-debugrel
Classifier: Environment :: No Input/Output (Daemon)
Classifier: Intended Audience :: End Users/Desktop
Classifier: License :: OSI Approved :: Apache Software License
Classifier: Operating System :: OS Independent
Classifier: Topic :: Multimedia :: Sound/Audio :: Players
Requires-Python: >=3.9
License-File: LICENSE
Requires-Dist: mopidy>=3.4.1
Requires-Dist: pykka>=3.1.1
